JPG2HEIF/__init__.py
JPG2HEIF/app.py
JPG2HEIF/cli.py
JPG2HEIF/converter.py
jpg2heif-0.1.8.dist-info/METADATA
jpg2heif-0.1.8.dist-info/WHEEL
jpg2heif-0.1.8.dist-info/entry_points.txt
jpg2heif-0.1.8.dist-info/top_level.txt
jpg2heif-0.1.8.dist-info/RECORD
