Metadata-Version: 2.1
Name: jpg2heif
Version: 0.1.8
Summary: A package to convert JPG images to HEIF format
Home-page: https://github.com/Devasy23/JPG2HEIF
Author: Devasy Patel
Author-email: patel.devasy.23@gmail.com
License: UNKNOWN
Platform: UNKNOWN
Classifier: Programming Language :: Python :: 3
Classifier: License :: OSI Approved :: MIT License
Classifier: Operating System :: OS Independent
Requires-Python: >=3.6
Requires-Dist: Pillow
Requires-Dist: pillow-heif
Requires-Dist: streamlit
